crowelang/__init__.py
crowelang/cli.py
crowelang/compiler.py
crowelang-1.0.0.dist-info/licenses/LICENSE
crowelang-1.0.0.dist-info/licenses/LICENSE.old
crowelang-1.0.0.dist-info/METADATA
crowelang-1.0.0.dist-info/WHEEL
crowelang-1.0.0.dist-info/entry_points.txt
crowelang-1.0.0.dist-info/top_level.txt
crowelang-1.0.0.dist-info/RECORD
