Metadata-Version: 2.4
Name: crowelang
Version: 1.0.0
Summary: Professional quantitative trading DSL for strategy development and execution
Home-page: https://github.com/MichaelCrowe11/crowe-lang
Author: Michael Benjamin Crowe
Author-email: Michael Benjamin Crowe <michael.crowe@crowelang.com>
License: Proprietary
Project-URL: Homepage, https://crowelang.com
Project-URL: Documentation, https://crowelang.com/docs
Project-URL: Repository, https://github.com/MichaelCrowe11/crowe-lang
Project-URL: Bug Tracker, https://github.com/MichaelCrowe11/crowe-lang/issues
Project-URL: Pricing, https://crowelang.com/pricing
Project-URL: Support, https://crowelang.com/support
Keywords: trading,quantitative,finance,strategy,dsl,compiler,algotrading
Classifier: Development Status :: 5 - Production/Stable
Classifier: Intended Audience :: Financial and Insurance Industry
Classifier: Intended Audience :: Developers
Classifier: Topic :: Office/Business :: Financial :: Investment
Classifier: Topic :: Software Development :: Compilers
Classifier: License :: Other/Proprietary License
Classifier: Programming Language :: Python :: 3
Classifier: Programming Language :: Python :: 3.8
Classifier: Programming Language :: Python :: 3.9
Classifier: Programming Language :: Python :: 3.10
Classifier: Programming Language :: Python :: 3.11
Classifier: Programming Language :: Python :: 3.12
Classifier: Operating System :: OS Independent
Requires-Python: >=3.8
License-File: LICENSE
License-File: LICENSE.old
Requires-Dist: click>=8.0.0
Requires-Dist: requests>=2.28.0
Requires-Dist: pydantic>=2.0.0
Requires-Dist: numpy>=1.20.0
Requires-Dist: pandas>=1.3.0
Requires-Dist: PyYAML>=6.0
Provides-Extra: dev
Requires-Dist: pytest>=7.0.0; extra == "dev"
Requires-Dist: pytest-cov>=4.0.0; extra == "dev"
Requires-Dist: black>=22.0.0; extra == "dev"
Requires-Dist: mypy>=1.0.0; extra == "dev"
Requires-Dist: flake8>=5.0.0; extra == "dev"
Dynamic: author
Dynamic: home-page
Dynamic: license-file
Dynamic: requires-python
